setup.py
zonediff.py
python_zonediff.egg-info/PKG-INFO
python_zonediff.egg-info/SOURCES.txt
python_zonediff.egg-info/dependency_links.txt
python_zonediff.egg-info/top_level.txt