Metadata-Version: 1.1
Name: python-zonediff
Version: 1.0
Summary: Library and commandline tool to create logical diffs of zonefiles
Home-page: http://github.com/seveas/python-zonediff
Author: Dennis Kaarsemaker
Author-email: dennis@kaarsemaker.net
License: UNKNOWN
Platform: UNKNOWN
Classifier: Intended Audience :: Developers
Classifier: Intended Audience :: System Administrators
Classifier: Operating System :: OS Independent
Classifier: Topic :: Internet :: Name Service (DNS)
Classifier: Topic :: Software Development
